django_devsync/__init__.py
django_devsync/__main__.py
django_devsync/main.py
django_devsync/args/__init__.py
django_devsync/args/utils.py
django_devsync/core/__init__.py
django_devsync/core/database.py
django_devsync/core/django_setup.py
django_devsync/core/migrations.py
django_devsync/core/sync_schema.py
django_devsync/core/utils.py
django_devsync-0.1.2.dist-info/licenses/LICENSE
django_devsync-0.1.2.dist-info/METADATA
django_devsync-0.1.2.dist-info/WHEEL
django_devsync-0.1.2.dist-info/entry_points.txt
django_devsync-0.1.2.dist-info/top_level.txt
django_devsync-0.1.2.dist-info/RECORD
