Metadata-Version: 2.4
Name: django-devsync
Version: 0.1.2
Summary: Wipe migrations, reset the dev database, and sync Django models — for dev mode only.
Requires-Python: >=3.8
License-File: LICENSE
Requires-Dist: django>=4.0
Dynamic: license-file
